texthandler/__init__.py
texthandler/api.py
texthandler/apps/__init__.py
texthandler/apps/model.py
texthandler-0.0.3.dist-info/METADATA
texthandler-0.0.3.dist-info/WHEEL
texthandler-0.0.3.dist-info/entry_points.txt
texthandler-0.0.3.dist-info/top_level.txt
texthandler-0.0.3.dist-info/RECORD
