Metadata-Version: 2.1
Name: texthandler
Version: 0.0.3
Summary: ok
Home-page: https://github.com/private_repo/
Author: slipper
Author-email: r2fscg@gmail.com
License: UNKNOWN
Platform: UNKNOWN
Classifier: Programming Language :: Python :: 3
Classifier: License :: OSI Approved :: MIT License
Classifier: Operating System :: OS Independent
Requires-Dist: codefast
Requires-Dist: premium
Requires-Dist: fastapi
Requires-Dist: uvicorn
Requires-Dist: torch
